Shynatime/ShTime.py
Shynatime/__init__.py
ShynaTime-0.15.dist-info/LICENSE
ShynaTime-0.15.dist-info/METADATA
ShynaTime-0.15.dist-info/WHEEL
ShynaTime-0.15.dist-info/top_level.txt
ShynaTime-0.15.dist-info/RECORD
