Metadata-Version: 2.1
Name: ShynaTime
Version: 0.15
Summary: Shyna Backend Functionality Package For Time manipulation
Author: Shivam Sharma
Author-email: shivamsharma1913@gmail.com
License-File: LICENSE
Requires-Dist: datefinder
Requires-Dist: datetime
Requires-Dist: python-dateutil
Requires-Dist: setuptools
Requires-Dist: wheel
